README.md
setup.cfg
setup.py
pulpo/__init__.py
pulpo/bandit_factory.py
pulpo/pulpo.py
pulpo.egg-info/PKG-INFO
pulpo.egg-info/SOURCES.txt
pulpo.egg-info/dependency_links.txt
pulpo.egg-info/requires.txt
pulpo.egg-info/top_level.txt
pulpo.egg-info/zip-safe
pulpo/bandits/__init__.py
pulpo/bandits/beta_thompson.py
pulpo/bandits/dataclasses.py
pulpo/bandits/epsilon_greedy.py
pulpo/bandits/guassian_thompson.py
pulpo/bandits/online_bandits.py
pulpo/constants/__init__.py
pulpo/constants/fields.py
tests/__init__.py
tests/test_bandit_factory.py
tests/test_pulpo.py
tests/bandits/__init__.py
tests/bandits/test_beta_thompson.py
tests/bandits/test_epsilon_greedy.py
tests/bandits/test_gaussian_thompson.py