Metadata-Version: 2.1
Name: pulpo
Version: 0.0.1
Summary: Multi-Arm-Bandit library
Home-page: https://github.com/pm3310/pulpo
Author: Pavlos Mitsoulis Ntompos, Fedor Alexandre Parfenov
Author-email: p.mitsoulis@gmail.com
License: MIT
Keywords: multi-arm-bandit reinforcement-learning machine-learning aws
Platform: UNKNOWN
Classifier: Development Status :: 4 - Beta
Classifier: License :: OSI Approved :: MIT License
Classifier: Intended Audience :: Developers
Classifier: Intended Audience :: Science/Research
Classifier: Natural Language :: English
Classifier: Programming Language :: Python :: 3
Classifier: Programming Language :: Python :: 3.5
Classifier: Programming Language :: Python :: 3.6
Classifier: Programming Language :: Python :: 3.7
Classifier: Topic :: Scientific/Engineering
Classifier: Topic :: Scientific/Engineering :: Artificial Intelligence
Requires-Python: ~=3.6
